hellopy/__init__.py
hellopy/collision.py
hellopy/events.py
hellopy/key.py
hellopy/mouse.py
hellopy/resource.py
hellopy/sound.py
hellopy/util.py
hellopy/window.py
hellopy/gameobject/__init__.py
hellopy/gameobject/circle.py
hellopy/gameobject/ellipse.py
hellopy/gameobject/gameobject.py
hellopy/gameobject/line.py
hellopy/gameobject/polygon.py
hellopy/gameobject/rectangle.py
hellopy/gameobject/sprite.py
hellopy/gameobject/test.py
hellopy/gameobject/text.py
hellopy/gameobject/triangle.py
hellopy/onlydemos/LoongPy.py
hellopy/onlydemos/__init__.py
hellopy/onlydemos/christmas.py
onlyshow/LoongPy.py
onlyshow/__init__.py
onlyshow/pumpkin.py
HelloPyOnly-0.1.29.dist-info/METADATA
HelloPyOnly-0.1.29.dist-info/WHEEL
HelloPyOnly-0.1.29.dist-info/top_level.txt
HelloPyOnly-0.1.29.dist-info/RECORD
